s5cmdpy/__init__.py
s5cmdpy/s5cmd_runner.py
s5cmdpy/uni_logger_standalone.py
s5cmdpy-0.2.7.dist-info/METADATA
s5cmdpy-0.2.7.dist-info/WHEEL
s5cmdpy-0.2.7.dist-info/RECORD
