Metadata-Version: 2.1
Name: s5cmdpy
Version: 0.2.7
Summary: python binding for using s5cmd to download and upload files to s3 efficiently
Author: yada
Author-email: trojblue@gmail.com
Requires-Python: >=3.10,<4.0
Classifier: Programming Language :: Python :: 3
Classifier: Programming Language :: Python :: 3.10
Classifier: Programming Language :: Python :: 3.11
Classifier: Programming Language :: Python :: 3.12
Classifier: Programming Language :: Python :: 3.13
